cortex/__init__.py
cortex/__main__.py
cortex/feature_types.py
cortex/participant_ext.py
cortex/primary/__init__.py
cortex/primary/acc_jerk.py
cortex/primary/game_level_scores.py
cortex/primary/screen_active.py
cortex/primary/significant_locations.py
cortex/primary/survey_scores.py
cortex/primary/trips.py
cortex/raw/__init__.py
cortex/raw/accelerometer.py
cortex/raw/ambient_light.py
cortex/raw/analytics.py
cortex/raw/balloon_risk.py
cortex/raw/bluetooth.py
cortex/raw/calls.py
cortex/raw/cats_and_dogs.py
cortex/raw/dcog.py
cortex/raw/device_motion.py
cortex/raw/device_state.py
cortex/raw/device_usage.py
cortex/raw/digit_span.py
cortex/raw/fragmented_letters.py
cortex/raw/funny_memory.py
cortex/raw/gps.py
cortex/raw/gyroscope.py
cortex/raw/jewels_a.py
cortex/raw/jewels_b.py
cortex/raw/messages_usage.py
cortex/raw/nearby_device.py
cortex/raw/phone_usage.py
cortex/raw/pop_the_bubbles.py
cortex/raw/screen_state.py
cortex/raw/sleep.py
cortex/raw/sms.py
cortex/raw/spatial_span.py
cortex/raw/steps.py
cortex/raw/survey.py
cortex/raw/telephony.py
cortex/raw/trails_b.py
cortex/raw/visits.py
cortex/raw/voice_survey.py
cortex/run.py
cortex/secondary/__init__.py
cortex/secondary/app_time.py
cortex/secondary/battery_level.py
cortex/secondary/call_degree.py
cortex/secondary/call_duration.py
cortex/secondary/call_number.py
cortex/secondary/data_quality.py
cortex/secondary/entropy.py
cortex/secondary/game_results.py
cortex/secondary/healthkit_sleep_duration.py
cortex/secondary/hometime.py
cortex/secondary/inactive_duration.py
cortex/secondary/nearby_device_count.py
cortex/secondary/screen_duration.py
cortex/secondary/screen_unlock_duration.py
cortex/secondary/screen_unlocks.py
cortex/secondary/screen_wakes.py
cortex/secondary/step_count.py
cortex/secondary/survey_results.py
cortex/secondary/text_degree.py
cortex/secondary/text_number.py
cortex/secondary/trip_distance.py
cortex/secondary/trip_duration.py
cortex/secondary/visit_time.py
cortex/study_ext.py
cortex/utils/__init__.py
lamp_cortex-2025.4.18.dist-info/LICENSE.md
lamp_cortex-2025.4.18.dist-info/METADATA
lamp_cortex-2025.4.18.dist-info/WHEEL
lamp_cortex-2025.4.18.dist-info/entry_points.txt
lamp_cortex-2025.4.18.dist-info/RECORD
