Metadata-Version: 2.3
Name: LAMP-cortex
Version: 2025.4.18
Summary: The Cortex data analysis toolkit for the LAMP Platform.
License: BSD-3-Clause
Keywords: LAMP Cortex
Author: Division of Digital Psychiatry at Beth Israel Deaconess Medical Center
Author-email: team@digitalpsych.org
Requires-Python: >=3.8,<4.0
Classifier: License :: OSI Approved :: BSD License
Classifier: Programming Language :: Python :: 3
Classifier: Programming Language :: Python :: 3.8
Classifier: Programming Language :: Python :: 3.9
Classifier: Programming Language :: Python :: 3.10
Classifier: Programming Language :: Python :: 3.11
Classifier: Programming Language :: Python :: 3.12
Classifier: Programming Language :: Python :: 3.13
Requires-Dist: DateTime (>=4.3,<5.0)
Requires-Dist: LAMP-core (>=2021.5.18,<2022.0.0)
Requires-Dist: altair (>=4.1.0,<5.0.0)
Requires-Dist: compress-pickle (>=2.0.1,<3.0.0)
Requires-Dist: fastdtw (>=0.3.4,<0.4.0)
Requires-Dist: geopy (>=2.1.0,<3.0.0)
Requires-Dist: matplotlib (>=3.9.0,<4.0.0)
Requires-Dist: numpy (>=1.20.3,<2.0.0)
Requires-Dist: pandas (>=1.2.4,<2.0.0)
Requires-Dist: pymongo (>=4.1.1,<5.0.0)
Requires-Dist: pytz (>=2021.1,<2022.0)
Requires-Dist: pyyaml (>=6.0.2,<7.0.0)
Requires-Dist: requests (>=2.16.2,<3.0.0)
Requires-Dist: scikit-learn (>=1.5.2,<2.0.0)
Requires-Dist: scipy (>=1.14.1,<2.0.0)
Requires-Dist: seaborn (>=0.12.0,<0.13.0)
Requires-Dist: statsmodels (>=0.14.4,<0.15.0)
Requires-Dist: tzwhere (>=3.0.3,<4.0.0)
Project-URL: Bug Tracker, https://github.com/BIDMCDigitalPsychiatry/LAMP-platform/issues
Project-URL: Documentation, https://docs.lamp.digital
Project-URL: Homepage, https://docs.lamp.digital
Project-URL: Repository, https://github.com/BIDMCDigitalPsychiatry/LAMP-cortex
